<?xml version="1.0" encoding="UTF-8"?>
<beans xmlns="http://www.springframework.org/schema/beans"
       xmlns:xsi="http://www.w3.org/2001/XMLSchema-instance"
       xmlns:mybatis-spring="http://mybatis.org/schema/mybatis-spring"
       xmlns:tx="http://www.springframework.org/schema/tx"
       xsi:schemaLocation="http://mybatis.org/schema/mybatis-spring http://mybatis.org/schema/mybatis-spring-1.2.xsd
		http://www.springframework.org/schema/beans http://www.springframework.org/schema/beans/spring-beans.xsd
		http://www.springframework.org/schema/tx http://www.springframework.org/schema/tx/spring-tx-4.3.xsd">

    <!-- Root Context: defines shared resources visible to all other web components -->

    <!-- DB Setting -->
    <bean id="propertyConfigurer"
          class="org.springframework.beans.factory.config.PropertyPlaceholderConfigurer">
        <property name="location" value="classpath:db.properties"/>
    </bean>

<!--     <bean id="dataSource" -->
<!--           class="org.springframework.jdbc.datasource.DriverManagerDataSource"> -->
<!--         <property name="driverClassName" value="${driverClassName}"/> -->
<!--         <property name="url" value="${url}"/> -->
<!--         <property name="username" value="${username}"/> -->
<!--         <property name="password" value="${password}"/> -->
<!--     </bean> -->

    <bean id="dataSource" class="org.apache.tomcat.dbcp.dbcp2.BasicDataSource"> 
        <property name="driverClassName" value="${driverClassName}"/>
        <property name="url" value="${url}"/>
        <property name="username" value="${username}"/>
        <property name="password" value="${password}"/>
    </bean>


    <!-- myBatis Setting -->
    <bean id="sqlSessionFactory" class="org.mybatis.spring.SqlSessionFactoryBean">
        <property name="dataSource" ref="dataSource"/>
        <property name="configLocation" value="classpath:/myBatis/config/mybatisConfig.xml"/>
        <property name="mapperLocations" value="classpath:/myBatis/mapper/*.xml"/>
    </bean>

    <bean id="sqlSessionTemplate" class="org.mybatis.spring.SqlSessionTemplate">
        <constructor-arg ref="sqlSessionFactory"/>
    </bean>

    <mybatis-spring:scan base-package="com.pknu.pass.*.dao "/>

    <!-- Transaction Setting -->
    <tx:annotation-driven/>

    <bean id="transactionManager"
          class="org.springframework.jdbc.datasource.DataSourceTransactionManager">
        <property name="dataSource" ref="dataSource"/>
    </bean>

</beans>
